{
  "version": "7",
  "dialect": "postgresql",
  "entries": [
    {
      "idx": 0,
      "version": "7",
      "when": 1776623531293,
      "tag": "0000_burly_maddog",
      "breakpoints": true
    },
    {
      "idx": 1,
      "version": "7",
      "when": 1776676840695,
      "tag": "0001_sprint3bis_foundation",
      "breakpoints": true
    },
    {
      "idx": 2,
      "version": "7",
      "when": 1776790811771,
      "tag": "0002_clumsy_doctor_faustus",
      "breakpoints": true
    },
    {
      "idx": 3,
      "version": "7",
      "when": 1776792405430,
      "tag": "0003_same_ben_parker",
      "breakpoints": true
    },
    {
      "idx": 4,
      "version": "7",
      "when": 1776846512205,
      "tag": "0004_worried_kate_bishop",
      "breakpoints": true
    },
    {
      "idx": 5,
      "version": "7",
      "when": 1776856777907,
      "tag": "0005_busy_roxanne_simpson",
      "breakpoints": true
    },
    {
      "idx": 6,
      "version": "7",
      "when": 1776858327649,
      "tag": "0006_wet_silhouette",
      "breakpoints": true
    },
    {
      "idx": 7,
      "version": "7",
      "when": 1745309600000,
      "tag": "0007_wave5_hooks_rotation",
      "breakpoints": true
    },
    {
      "idx": 8,
      "version": "7",
      "when": 1776861822516,
      "tag": "0008_whole_ma_gnuci",
      "breakpoints": true
    },
    {
      "idx": 9,
      "version": "7",
      "when": 1776879000000,
      "tag": "0009_organizations_default_workspace",
      "breakpoints": true
    },
    {
      "idx": 10,
      "version": "7",
      "when": 1776904200000,
      "tag": "0010_databases_runtime_surface",
      "breakpoints": true
    },
    {
      "idx": 11,
      "version": "7",
      "when": 1776953400000,
      "tag": "0011_framework_build_surface",
      "breakpoints": true
    },
    {
      "idx": 12,
      "version": "7",
      "when": 1776960000000,
      "tag": "0012_databases_public_port_unique",
      "breakpoints": true
    },
    {
      "idx": 13,
      "version": "7",
      "when": 1777015052779,
      "tag": "0013_drift_catchup",
      "breakpoints": true
    },
    {
      "idx": 14,
      "version": "7",
      "when": 1777015082712,
      "tag": "0014_provider_repos",
      "breakpoints": true
    },
    {
      "idx": 15,
      "version": "7",
      "when": 1777018685844,
      "tag": "0015_notification_read_state",
      "breakpoints": true
    },
    {
      "idx": 16,
      "version": "7",
      "when": 1777032130262,
      "tag": "0016_bitter_ogun",
      "breakpoints": true
    },
    {
      "idx": 17,
      "version": "7",
      "when": 1777034898457,
      "tag": "0017_complex_maddog",
      "breakpoints": true
    }
  ]
}